test_parlant/__init__.py
test_parlant/server/mcp/__init__.py
test_parlant/server/mcp/prompt.py
test_parlant/server/router/__init__.py
test_parlant/server/router/prompt.py
test_parlant-0.1.1.dist-info/METADATA
test_parlant-0.1.1.dist-info/WHEEL
test_parlant-0.1.1.dist-info/top_level.txt
test_parlant-0.1.1.dist-info/RECORD
